gitamite/__init__.py
gitamite/glearn.py
gitamite/helper.py
gitamite/moodle.py
gitamite-1.3.0.dist-info/LICENSE
gitamite-1.3.0.dist-info/METADATA
gitamite-1.3.0.dist-info/WHEEL
gitamite-1.3.0.dist-info/top_level.txt
gitamite-1.3.0.dist-info/RECORD
