Metadata-Version: 2.1
Name: gitamite
Version: 1.3.0
Summary: This is GITAM library for Moodle and Glearn.
Home-page: https://github.com/innovation-center-gitam-hyd/gitamite-library
Author: Sumanth Perambuduri
Author-email: sumanthpera3@gmail.com
License: MIT
Platform: UNKNOWN
License-File: LICENSE
Requires-Dist: requests
Requires-Dist: beautifulsoup4
